hulalei/__init__.py
hulalei/add.py
hulalei/substract.py
hulalei/extras/__init__.py
hulalei/extras/divide.py
hulalei/extras/multiply.py
verysimplemodule/__init__.py
verysimplemodule/add.py
verysimplemodule/substract.py
verysimplemodule/extras/__init__.py
verysimplemodule/extras/divide.py
verysimplemodule/extras/multiply.py
hulalei-0.0.3.dist-info/METADATA
hulalei-0.0.3.dist-info/WHEEL
hulalei-0.0.3.dist-info/top_level.txt
hulalei-0.0.3.dist-info/RECORD
